ysyx_digital_lab1_code/lab1_mux21.v
module lab1_mux21 (
    input a,
    input b,
    input s,
    output y
);
assign y = (~s & a) | (s & b);
    
endmodule

ysyx_digital_lab1_code/dump.vcd
$version Generated by VerilatedVcd $end
$date Fri Mar 25 23:06:47 2022 $end
$timescale 1s $end

 $scope module TOP $end
  $var wire  1 # a $end
  $var wire  1 $ b $end
  $var wire  1 % s $end
  $var wire  1 & y $end
  $scope module lab1_mux21 $end
   $var wire  1 # a $end
   $var wire  1 $ b $end
   $var wire  1 % s $end
   $var wire  1 & y $end
  $upscope $end
 $upscope $end
$enddefinitions $end


#1
0#
0$
0%
0&
#2
1$
#3
1#
0$
1&
#4
1$
#5
0#
0$
1%
0&
#6
1$
1&
#7
1#
0$
0&
#8
1$
1&
